georideapilib/api.py
georideapilib/exception.py
georideapilib/socket.py
georideapilib/objects/GeoRideAccount.py
georideapilib/objects/GeoRideMaintenance.py
georideapilib/objects/GeoRideSharedTrip.py
georideapilib/objects/GeoRideSubscription.py
georideapilib/objects/GeoRideSubscription_CardInfo.py
georideapilib/objects/GeoRideTracker.py
georideapilib/objects/GeoRideTrackerBeacon.py
georideapilib/objects/GeoRideTrackerPosition.py
georideapilib/objects/GeoRideTrackerTrip.py
georideapilib/objects/GeoRideUser.py
georideapilib/objects/JsonMgtMetaClass.py
georideapilib/objects/__init__.py
georideapilib-1.2.0.dist-info/LICENSE
georideapilib-1.2.0.dist-info/METADATA
georideapilib-1.2.0.dist-info/WHEEL
georideapilib-1.2.0.dist-info/top_level.txt
georideapilib-1.2.0.dist-info/RECORD
