Metadata-Version: 2.1
Name: georideapilib
Version: 1.2.0
Summary: Lib to control GeoRide tracker devices with theire rest api
Home-page: https://github.com/hacf/georide-api
Download-URL: https://codeload.github.com/hacf/georide-api/tar.gz/1.0.0
Author: Matthieu DUVAL
Author-email: georideapilib@duval-dev.fr
Keywords: rest,georide,api,grutier,GeoRide
License-File: LICENSE
Requires-Dist: python-socketio[client] ==4.6.1
